{"metadata": {"dbt_schema_version": "https://schemas.getdbt.com/dbt/run-results/v4.json", "dbt_version": "1.5.0", "generated_at": "2023-12-08T11:29:12.212295Z", "invocation_id": "fe2d86e5-d072-4fef-bcde-d99998b8c68f", "env": {}}, "results": [{"status": "success", "timing": [{"name": "compile", "started_at": "2023-12-08T11:29:11.875554Z", "completed_at": "2023-12-08T11:29:12.054691Z"}, {"name": "execute", "started_at": "2023-12-08T11:29:12.125783Z", "completed_at": "2023-12-08T11:29:12.125806Z"}], "thread_id": "Thread-5", "execution_time": 0.28104496002197266, "adapter_response": {}, "message": null, "failures": null, "unique_id": "model.safegraph_project.VISIT_PANEL_SUMMARY"}, {"status": "success", "timing": [{"name": "compile", "started_at": "2023-12-08T11:29:11.914687Z", "completed_at": "2023-12-08T11:29:12.051480Z"}, {"name": "execute", "started_at": "2023-12-08T11:29:12.105408Z", "completed_at": "2023-12-08T11:29:12.107775Z"}], "thread_id": "Thread-4", "execution_time": 0.3213655948638916, "adapter_response": {}, "message": null, "failures": null, "unique_id": "model.safegraph_project.NORMALIZATION_STATS"}, {"status": "success", "timing": [{"name": "compile", "started_at": "2023-12-08T11:29:11.841914Z", "completed_at": "2023-12-08T11:29:12.049515Z"}, {"name": "execute", "started_at": "2023-12-08T11:29:12.151759Z", "completed_at": "2023-12-08T11:29:12.151775Z"}], "thread_id": "Thread-2", "execution_time": 0.3477489948272705, "adapter_response": {}, "message": null, "failures": null, "unique_id": "model.safegraph_project.CORE_POI_PATTERNS"}, {"status": "success", "timing": [{"name": "compile", "started_at": "2023-12-08T11:29:11.973140Z", "completed_at": "2023-12-08T11:29:12.100499Z"}, {"name": "execute", "started_at": "2023-12-08T11:29:12.177282Z", "completed_at": "2023-12-08T11:29:12.177301Z"}], "thread_id": "Thread-3", "execution_time": 0.3450641632080078, "adapter_response": {}, "message": null, "failures": null, "unique_id": "model.safegraph_project.HOME_PANEL_SUMMARY"}, {"status": "success", "timing": [{"name": "compile", "started_at": "2023-12-08T11:29:11.951106Z", "completed_at": "2023-12-08T11:29:12.059641Z"}, {"name": "execute", "started_at": "2023-12-08T11:29:12.183887Z", "completed_at": "2023-12-08T11:29:12.183907Z"}], "thread_id": "Thread-1", "execution_time": 0.3569173812866211, "adapter_response": {}, "message": null, "failures": null, "unique_id": "model.safegraph_project.BRAND_INFO"}], "elapsed_time": 8.665580034255981, "args": {"use_colors_file": true, "print": true, "version_check": true, "favor_state": false, "strict_mode": false, "compile": true, "cache_selected_only": false, "macro_debugging": false, "select": [], "indirect_selection": "eager", "log_format_file": "debug", "log_level": "info", "vars": {}, "which": "generate", "use_colors": true, "send_anonymous_usage_stats": true, "profiles_dir": "/opt/airflow/dags/dbt/projects/external_data/safegraph", "project_dir": "/opt/airflow/dags/dbt/projects/external_data/safegraph", "log_format": "default", "introspect": true, "write_json": true, "printer_width": 80, "partial_parse": true, "quiet": false, "warn_error_options": {"include": [], "exclude": []}, "enable_legacy_logger": false, "populate_cache": true, "log_level_file": "debug", "log_path": "/opt/airflow/dags/dbt/projects/external_data/safegraph/logs", "exclude": [], "static_parser": true, "defer": false}}